<?xml version="1.0" encoding="UTF-8"?>
<config xmlns="http://www.knime.org/2008/09/XMLConfig" xmlns:xsi="http://www.w3.org/2001/XMLSchema-instance" xsi:schemaLocation="http://www.knime.org/2008/09/XMLConfig http://www.knime.org/XMLConfig_2008_09.xsd" key="viewRepresentation">
    <entry key="showLegend" type="xboolean" value="false"/>
    <entry key="autoRange" type="xboolean" value="true"/>
    <entry key="useDomainInformation" type="xboolean" value="false"/>
    <entry key="showGrid" type="xboolean" value="false"/>
    <entry key="showCrosshair" type="xboolean" value="false"/>
    <entry key="snapToPoints" type="xboolean" value="false"/>
    <entry key="resizeToWindow" type="xboolean" value="true"/>
    <entry key="enableViewConfiguration" type="xboolean" value="true"/>
    <entry key="enableTitleChange" type="xboolean" value="true"/>
    <entry key="enableSubtitleChange" type="xboolean" value="true"/>
    <entry key="enableXColumnChange" type="xboolean" value="true"/>
    <entry key="enableYColumnChange" type="xboolean" value="true"/>
    <entry key="enableXAxisLabelEdit" type="xboolean" value="true"/>
    <entry key="enableYAxisLabelEdit" type="xboolean" value="true"/>
    <entry key="enableDotSizeChange" type="xboolean" value="false"/>
    <entry key="enablePanning" type="xboolean" value="true"/>
    <entry key="enableZooming" type="xboolean" value="false"/>
    <entry key="enableDragZooming" type="xboolean" value="false"/>
    <entry key="showZoomResetButton" type="xboolean" value="false"/>
    <entry key="enableSelection" type="xboolean" value="false"/>
    <entry key="enableRectangleSelection" type="xboolean" value="false"/>
    <entry key="enableLassoSelection" type="xboolean" value="false"/>
    <entry key="imageWidth" type="xint" value="800"/>
    <entry key="imageHeight" type="xint" value="600"/>
    <entry key="backgroundColor" type="xstring" value="rgba(255,255,255,1.0)"/>
    <entry key="dataAreaColor" type="xstring" value="rgba(255,255,255,1.0)"/>
    <entry key="gridColor" type="xstring" value="rgba(230,230,230,1.0)"/>
    <entry key="hasDataset" type="xboolean" value="true"/>
    <config key="dataset">
        <entry key="tableID" type="xstring" value="bb776c49-8ef9-4832-ab78-f6474682a9c6"/>
        <config key="columnKeys">
            <entry key="array-size" type="xint" value="5"/>
            <entry key="0" type="xstring" value="rowin"/>
            <entry key="1" type="xstring" value="CI Bound"/>
            <entry key="2" type="xstring" value="Cl Bound"/>
            <entry key="3" type="xstring" value="acf"/>
            <entry key="4" type="xstring" value="pacf"/>
        </config>
        <config key="columnColors">
            <entry key="array-size" type="xint" value="5"/>
            <entry key="0" type="xstring" isnull="true" value=""/>
            <entry key="1" type="xstring" value="#FF4040"/>
            <entry key="2" type="xstring" value="#FF4040"/>
            <entry key="3" type="xstring" value="#000000"/>
            <entry key="4" type="xstring" value="#000000"/>
        </config>
        <config key="dateTimeFormats">
            <entry key="array-size" type="xint" value="5"/>
            <entry key="0" type="xstring" isnull="true" value=""/>
            <entry key="1" type="xstring" isnull="true" value=""/>
            <entry key="2" type="xstring" isnull="true" value=""/>
            <entry key="3" type="xstring" isnull="true" value=""/>
            <entry key="4" type="xstring" isnull="true" value=""/>
        </config>
        <entry key="colPropsSize" type="xint" value="0"/>
        <entry key="numRows" type="xint" value="61"/>
        <config key="row_0">
            <entry key="rowKey" type="xstring" value="0"/>
            <config key="values">
                <entry key="array-size" type="xint" value="5"/>
                <entry key="0" type="xstring" value="0.0"/>
                <entry key="1" type="xstring" value="0.10041384183739775"/>
                <entry key="2" type="xstring" value="-0.10041384183739775"/>
                <entry key="3" type="xstring" value="1.0"/>
                <entry key="4" type="xstring" value="1.0"/>
            </config>
            <entry key="numProperties" type="xint" value="1"/>
            <config key="property_0">
                <entry key="key" type="xstring" value="color"/>
                <entry key="value" type="xstring" value="#404040"/>
            </config>
        </config>
        <config key="row_1">
            <entry key="rowKey" type="xstring" value="1"/>
            <config key="values">
                <entry key="array-size" type="xint" value="5"/>
                <entry key="0" type="xstring" value="1.0"/>
                <entry key="1" type="xstring" value="0.10054587850434511"/>
                <entry key="2" type="xstring" value="-0.10054587850434511"/>
                <entry key="3" type="xstring" value="0.29809311251881876"/>
                <entry key="4" type="xstring" value="0.2988775680780788"/>
            </config>
            <entry key="numProperties" type="xint" value="1"/>
            <config key="property_0">
                <entry key="key" type="xstring" value="color"/>
                <entry key="value" type="xstring" value="#404040"/>
            </config>
        </config>
        <config key="row_2">
            <entry key="rowKey" type="xstring" value="2"/>
            <config key="values">
                <entry key="array-size" type="xint" value="5"/>
                <entry key="0" type="xstring" value="2.0"/>
                <entry key="1" type="xstring" value="0.10067843739975277"/>
                <entry key="2" type="xstring" value="-0.10067843739975277"/>
                <entry key="3" type="xstring" value="0.33617545168206814"/>
                <entry key="4" type="xstring" value="0.27300895328815006"/>
            </config>
            <entry key="numProperties" type="xint" value="1"/>
            <config key="property_0">
                <entry key="key" type="xstring" value="color"/>
                <entry key="value" type="xstring" value="#404040"/>
            </config>
        </config>
        <config key="row_3">
            <entry key="rowKey" type="xstring" value="3"/>
            <config key="values">
                <entry key="array-size" type="xint" value="5"/>
                <entry key="0" type="xstring" value="3.0"/>
                <entry key="1" type="xstring" value="0.10081152197523338"/>
                <entry key="2" type="xstring" value="-0.10081152197523338"/>
                <entry key="3" type="xstring" value="0.2959583507759663"/>
                <entry key="4" type="xstring" value="0.17000653310795155"/>
            </config>
            <entry key="numProperties" type="xint" value="1"/>
            <config key="property_0">
                <entry key="key" type="xstring" value="color"/>
                <entry key="value" type="xstring" value="#404040"/>
            </config>
        </config>
        <config key="row_4">
            <entry key="rowKey" type="xstring" value="4"/>
            <config key="values">
                <entry key="array-size" type="xint" value="5"/>
                <entry key="0" type="xstring" value="4.0"/>
                <entry key="1" type="xstring" value="0.10094513571442253"/>
                <entry key="2" type="xstring" value="-0.10094513571442253"/>
                <entry key="3" type="xstring" value="0.32496543454259424"/>
                <entry key="4" type="xstring" value="0.17942896874331601"/>
            </config>
            <entry key="numProperties" type="xint" value="1"/>
            <config key="property_0">
                <entry key="key" type="xstring" value="color"/>
                <entry key="value" type="xstring" value="#404040"/>
            </config>
        </config>
        <config key="row_5">
            <entry key="rowKey" type="xstring" value="5"/>
            <config key="values">
                <entry key="array-size" type="xint" value="5"/>
                <entry key="0" type="xstring" value="5.0"/>
                <entry key="1" type="xstring" value="0.10107928213336174"/>
                <entry key="2" type="xstring" value="-0.10107928213336174"/>
                <entry key="3" type="xstring" value="0.3102916324436218"/>
                <entry key="4" type="xstring" value="0.13863981743975318"/>
            </config>
            <entry key="numProperties" type="xint" value="1"/>
            <config key="property_0">
                <entry key="key" type="xstring" value="color"/>
                <entry key="value" type="xstring" value="#404040"/>
            </config>
        </config>
        <config key="row_6">
            <entry key="rowKey" type="xstring" value="6"/>
            <config key="values">
                <entry key="array-size" type="xint" value="5"/>
                <entry key="0" type="xstring" value="6.0"/>
                <entry key="1" type="xstring" value="0.10121396478088716"/>
                <entry key="2" type="xstring" value="-0.10121396478088716"/>
                <entry key="3" type="xstring" value="0.28576168769989063"/>
                <entry key="4" type="xstring" value="0.08713842992783963"/>
            </config>
            <entry key="numProperties" type="xint" value="1"/>
            <config key="property_0">
                <entry key="key" type="xstring" value="color"/>
                <entry key="value" type="xstring" value="#404040"/>
            </config>
        </config>
        <config key="row_7">
            <entry key="rowKey" type="xstring" value="7"/>
            <config key="values">
                <entry key="array-size" type="xint" value="5"/>
                <entry key="0" type="xstring" value="7.0"/>
                <entry key="1" type="xstring" value="0.10134918723902375"/>
                <entry key="2" type="xstring" value="-0.10134918723902375"/>
                <entry key="3" type="xstring" value="0.34119281473429697"/>
                <entry key="4" type="xstring" value="0.156556462649374"/>
            </config>
            <entry key="numProperties" type="xint" value="1"/>
            <config key="property_0">
                <entry key="key" type="xstring" value="color"/>
                <entry key="value" type="xstring" value="#404040"/>
            </config>
        </config>
        <config key="row_8">
            <entry key="rowKey" type="xstring" value="8"/>
            <config key="values">
                <entry key="array-size" type="xint" value="5"/>
                <entry key="0" type="xstring" value="8.0"/>
                <entry key="1" type="xstring" value="0.10148495312338555"/>
                <entry key="2" type="xstring" value="-0.10148495312338555"/>
                <entry key="3" type="xstring" value="0.19913597465196897"/>
                <entry key="4" type="xstring" value="-0.04998350502647099"/>
            </config>
            <entry key="numProperties" type="xint" value="1"/>
            <config key="property_0">
                <entry key="key" type="xstring" value="color"/>
                <entry key="value" type="xstring" value="#404040"/>
            </config>
        </config>
        <config key="row_9">
            <entry key="rowKey" type="xstring" value="9"/>
            <config key="values">
                <entry key="array-size" type="xint" value="5"/>
                <entry key="0" type="xstring" value="9.0"/>
                <entry key="1" type="xstring" value="0.10162126608358167"/>
                <entry key="2" type="xstring" value="-0.10162126608358167"/>
                <entry key="3" type="xstring" value="0.24646176731115968"/>
                <entry key="4" type="xstring" value="0.023078498849819825"/>
            </config>
            <entry key="numProperties" type="xint" value="1"/>
            <config key="property_0">
                <entry key="key" type="xstring" value="color"/>
                <entry key="value" type="xstring" value="#404040"/>
            </config>
        </config>
        <config key="row_10">
            <entry key="rowKey" type="xstring" value="10"/>
            <config key="values">
                <entry key="array-size" type="xint" value="5"/>
                <entry key="0" type="xstring" value="10.0"/>
                <entry key="1" type="xstring" value="0.10175812980362833"/>
                <entry key="2" type="xstring" value="-0.10175812980362833"/>
                <entry key="3" type="xstring" value="0.21560838409657365"/>
                <entry key="4" type="xstring" value="0.008573963086323846"/>
            </config>
            <entry key="numProperties" type="xint" value="1"/>
            <config key="property_0">
                <entry key="key" type="xstring" value="color"/>
                <entry key="value" type="xstring" value="#404040"/>
            </config>
        </config>
        <config key="row_11">
            <entry key="rowKey" type="xstring" value="11"/>
            <config key="values">
                <entry key="array-size" type="xint" value="5"/>
                <entry key="0" type="xstring" value="11.0"/>
                <entry key="1" type="xstring" value="0.10189554800236712"/>
                <entry key="2" type="xstring" value="-0.10189554800236712"/>
                <entry key="3" type="xstring" value="0.23016942466073526"/>
                <entry key="4" type="xstring" value="0.02382781665443809"/>
            </config>
            <entry key="numProperties" type="xint" value="1"/>
            <config key="property_0">
                <entry key="key" type="xstring" value="color"/>
                <entry key="value" type="xstring" value="#404040"/>
            </config>
        </config>
        <config key="row_12">
            <entry key="rowKey" type="xstring" value="12"/>
            <config key="values">
                <entry key="array-size" type="xint" value="5"/>
                <entry key="0" type="xstring" value="12.0"/>
                <entry key="1" type="xstring" value="0.1020335244338893"/>
                <entry key="2" type="xstring" value="-0.1020335244338893"/>
                <entry key="3" type="xstring" value="0.2418945328853682"/>
                <entry key="4" type="xstring" value="0.06261993548984161"/>
            </config>
            <entry key="numProperties" type="xint" value="1"/>
            <config key="property_0">
                <entry key="key" type="xstring" value="color"/>
                <entry key="value" type="xstring" value="#404040"/>
            </config>
        </config>
        <config key="row_13">
            <entry key="rowKey" type="xstring" value="13"/>
            <config key="values">
                <entry key="array-size" type="xint" value="5"/>
                <entry key="0" type="xstring" value="13.0"/>
                <entry key="1" type="xstring" value="0.10217206288796664"/>
                <entry key="2" type="xstring" value="-0.10217206288796664"/>
                <entry key="3" type="xstring" value="0.13907686011804762"/>
                <entry key="4" type="xstring" value="-0.07817190016868372"/>
            </config>
            <entry key="numProperties" type="xint" value="1"/>
            <config key="property_0">
                <entry key="key" type="xstring" value="color"/>
                <entry key="value" type="xstring" value="#404040"/>
            </config>
        </config>
        <config key="row_14">
            <entry key="rowKey" type="xstring" value="14"/>
            <config key="values">
                <entry key="array-size" type="xint" value="5"/>
                <entry key="0" type="xstring" value="14.0"/>
                <entry key="1" type="xstring" value="0.10231116719048859"/>
                <entry key="2" type="xstring" value="-0.10231116719048859"/>
                <entry key="3" type="xstring" value="0.24403494238484694"/>
                <entry key="4" type="xstring" value="0.08362722889891236"/>
            </config>
            <entry key="numProperties" type="xint" value="1"/>
            <config key="property_0">
                <entry key="key" type="xstring" value="color"/>
                <entry key="value" type="xstring" value="#404040"/>
            </config>
        </config>
        <config key="row_15">
            <entry key="rowKey" type="xstring" value="15"/>
            <config key="values">
                <entry key="array-size" type="xint" value="5"/>
                <entry key="0" type="xstring" value="15.0"/>
                <entry key="1" type="xstring" value="0.10245084120390606"/>
                <entry key="2" type="xstring" value="-0.10245084120390606"/>
                <entry key="3" type="xstring" value="0.16992491346582903"/>
                <entry key="4" type="xstring" value="0.012497636984691479"/>
            </config>
            <entry key="numProperties" type="xint" value="1"/>
            <config key="property_0">
                <entry key="key" type="xstring" value="color"/>
                <entry key="value" type="xstring" value="#404040"/>
            </config>
        </config>
        <config key="row_16">
            <entry key="rowKey" type="xstring" value="16"/>
            <config key="values">
                <entry key="array-size" type="xint" value="5"/>
                <entry key="0" type="xstring" value="16.0"/>
                <entry key="1" type="xstring" value="0.10259108882768189"/>
                <entry key="2" type="xstring" value="-0.10259108882768189"/>
                <entry key="3" type="xstring" value="0.16949511082185928"/>
                <entry key="4" type="xstring" value="-0.02098933750162457"/>
            </config>
            <entry key="numProperties" type="xint" value="1"/>
            <config key="property_0">
                <entry key="key" type="xstring" value="color"/>
                <entry key="value" type="xstring" value="#404040"/>
            </config>
        </config>
        <config key="row_17">
            <entry key="rowKey" type="xstring" value="17"/>
            <config key="values">
                <entry key="array-size" type="xint" value="5"/>
                <entry key="0" type="xstring" value="17.0"/>
                <entry key="1" type="xstring" value="0.102731913998748"/>
                <entry key="2" type="xstring" value="-0.102731913998748"/>
                <entry key="3" type="xstring" value="0.16443879406170958"/>
                <entry key="4" type="xstring" value="0.01597975383063826"/>
            </config>
            <entry key="numProperties" type="xint" value="1"/>
            <config key="property_0">
                <entry key="key" type="xstring" value="color"/>
                <entry key="value" type="xstring" value="#404040"/>
            </config>
        </config>
        <config key="row_18">
            <entry key="rowKey" type="xstring" value="18"/>
            <config key="values">
                <entry key="array-size" type="xint" value="5"/>
                <entry key="0" type="xstring" value="18.0"/>
                <entry key="1" type="xstring" value="0.10287332069196968"/>
                <entry key="2" type="xstring" value="-0.10287332069196968"/>
                <entry key="3" type="xstring" value="0.15112193388175035"/>
                <entry key="4" type="xstring" value="-0.015610648665020994"/>
            </config>
            <entry key="numProperties" type="xint" value="1"/>
            <config key="property_0">
                <entry key="key" type="xstring" value="color"/>
                <entry key="value" type="xstring" value="#404040"/>
            </config>
        </config>
        <config key="row_19">
            <entry key="rowKey" type="xstring" value="19"/>
            <config key="values">
                <entry key="array-size" type="xint" value="5"/>
                <entry key="0" type="xstring" value="19.0"/>
                <entry key="1" type="xstring" value="0.1030153129206168"/>
                <entry key="2" type="xstring" value="-0.1030153129206168"/>
                <entry key="3" type="xstring" value="0.15307940939273387"/>
                <entry key="4" type="xstring" value="0.0016775011881478188"/>
            </config>
            <entry key="numProperties" type="xint" value="1"/>
            <config key="property_0">
                <entry key="key" type="xstring" value="color"/>
                <entry key="value" type="xstring" value="#404040"/>
            </config>
        </config>
        <config key="row_20">
            <entry key="rowKey" type="xstring" value="20"/>
            <config key="values">
                <entry key="array-size" type="xint" value="5"/>
                <entry key="0" type="xstring" value="20.0"/>
                <entry key="1" type="xstring" value="0.1031578947368421"/>
                <entry key="2" type="xstring" value="-0.1031578947368421"/>
                <entry key="3" type="xstring" value="0.09325224975929046"/>
                <entry key="4" type="xstring" value="-0.04151081816656423"/>
            </config>
            <entry key="numProperties" type="xint" value="1"/>
            <config key="property_0">
                <entry key="key" type="xstring" value="color"/>
                <entry key="value" type="xstring" value="#404040"/>
            </config>
        </config>
        <config key="row_21">
            <entry key="rowKey" type="xstring" value="21"/>
            <config key="values">
                <entry key="array-size" type="xint" value="5"/>
                <entry key="0" type="xstring" value="21.0"/>
                <entry key="1" type="xstring" value="0.10330107023216706"/>
                <entry key="2" type="xstring" value="-0.10330107023216706"/>
                <entry key="3" type="xstring" value="0.15444209769741063"/>
                <entry key="4" type="xstring" value="0.01197584013910665"/>
            </config>
            <entry key="numProperties" type="xint" value="1"/>
            <config key="property_0">
                <entry key="key" type="xstring" value="color"/>
                <entry key="value" type="xstring" value="#404040"/>
            </config>
        </config>
        <config key="row_22">
            <entry key="rowKey" type="xstring" value="22"/>
            <config key="values">
                <entry key="array-size" type="xint" value="5"/>
                <entry key="0" type="xstring" value="22.0"/>
                <entry key="1" type="xstring" value="0.10344484353797487"/>
                <entry key="2" type="xstring" value="-0.10344484353797487"/>
                <entry key="3" type="xstring" value="0.07339462230888563"/>
                <entry key="4" type="xstring" value="-0.04745258791105086"/>
            </config>
            <entry key="numProperties" type="xint" value="1"/>
            <config key="property_0">
                <entry key="key" type="xstring" value="color"/>
                <entry key="value" type="xstring" value="#404040"/>
            </config>
        </config>
        <config key="row_23">
            <entry key="rowKey" type="xstring" value="23"/>
            <config key="values">
                <entry key="array-size" type="xint" value="5"/>
                <entry key="0" type="xstring" value="23.0"/>
                <entry key="1" type="xstring" value="0.10358921882601123"/>
                <entry key="2" type="xstring" value="-0.10358921882601123"/>
                <entry key="3" type="xstring" value="0.08643798519537349"/>
                <entry key="4" type="xstring" value="-0.034729924861091645"/>
            </config>
            <entry key="numProperties" type="xint" value="1"/>
            <config key="property_0">
                <entry key="key" type="xstring" value="color"/>
                <entry key="value" type="xstring" value="#404040"/>
            </config>
        </config>
        <config key="row_24">
            <entry key="rowKey" type="xstring" value="24"/>
            <config key="values">
                <entry key="array-size" type="xint" value="5"/>
                <entry key="0" type="xstring" value="24.0"/>
                <entry key="1" type="xstring" value="0.10373420030889277"/>
                <entry key="2" type="xstring" value="-0.10373420030889277"/>
                <entry key="3" type="xstring" value="0.05256221031972209"/>
                <entry key="4" type="xstring" value="-0.04940565557655595"/>
            </config>
            <entry key="numProperties" type="xint" value="1"/>
            <config key="property_0">
                <entry key="key" type="xstring" value="color"/>
                <entry key="value" type="xstring" value="#404040"/>
            </config>
        </config>
        <config key="row_25">
            <entry key="rowKey" type="xstring" value="25"/>
            <config key="values">
                <entry key="array-size" type="xint" value="5"/>
                <entry key="0" type="xstring" value="25.0"/>
                <entry key="1" type="xstring" value="0.10387979224062328"/>
                <entry key="2" type="xstring" value="-0.10387979224062328"/>
                <entry key="3" type="xstring" value="0.03788147991616005"/>
                <entry key="4" type="xstring" value="-0.049237203122633286"/>
            </config>
            <entry key="numProperties" type="xint" value="1"/>
            <config key="property_0">
                <entry key="key" type="xstring" value="color"/>
                <entry key="value" type="xstring" value="#404040"/>
            </config>
        </config>
        <config key="row_26">
            <entry key="rowKey" type="xstring" value="26"/>
            <config key="values">
                <entry key="array-size" type="xint" value="5"/>
                <entry key="0" type="xstring" value="26.0"/>
                <entry key="1" type="xstring" value="0.10402599891711795"/>
                <entry key="2" type="xstring" value="-0.10402599891711795"/>
                <entry key="3" type="xstring" value="-0.04116818810617541"/>
                <entry key="4" type="xstring" value="-0.1603708064596642"/>
            </config>
            <entry key="numProperties" type="xint" value="1"/>
            <config key="property_0">
                <entry key="key" type="xstring" value="color"/>
                <entry key="value" type="xstring" value="#404040"/>
            </config>
        </config>
        <config key="row_27">
            <entry key="rowKey" type="xstring" value="27"/>
            <config key="values">
                <entry key="array-size" type="xint" value="5"/>
                <entry key="0" type="xstring" value="27.0"/>
                <entry key="1" type="xstring" value="0.10417282467673585"/>
                <entry key="2" type="xstring" value="-0.10417282467673585"/>
                <entry key="3" type="xstring" value="-0.015792024768019244"/>
                <entry key="4" type="xstring" value="-0.04057120060388425"/>
            </config>
            <entry key="numProperties" type="xint" value="1"/>
            <config key="property_0">
                <entry key="key" type="xstring" value="color"/>
                <entry key="value" type="xstring" value="#404040"/>
            </config>
        </config>
        <config key="row_28">
            <entry key="rowKey" type="xstring" value="28"/>
            <config key="values">
                <entry key="array-size" type="xint" value="5"/>
                <entry key="0" type="xstring" value="28.0"/>
                <entry key="1" type="xstring" value="0.10432027390082049"/>
                <entry key="2" type="xstring" value="-0.10432027390082049"/>
                <entry key="3" type="xstring" value="0.08034800206929381"/>
                <entry key="4" type="xstring" value="0.09727760858026327"/>
            </config>
            <entry key="numProperties" type="xint" value="1"/>
            <config key="property_0">
                <entry key="key" type="xstring" value="color"/>
                <entry key="value" type="xstring" value="#404040"/>
            </config>
        </config>
        <config key="row_29">
            <entry key="rowKey" type="xstring" value="29"/>
            <config key="values">
                <entry key="array-size" type="xint" value="5"/>
                <entry key="0" type="xstring" value="29.0"/>
                <entry key="1" type="xstring" value="0.1044683510142491"/>
                <entry key="2" type="xstring" value="-0.1044683510142491"/>
                <entry key="3" type="xstring" value="0.0036490308708416997"/>
                <entry key="4" type="xstring" value="0.0032126484733870932"/>
            </config>
            <entry key="numProperties" type="xint" value="1"/>
            <config key="property_0">
                <entry key="key" type="xstring" value="color"/>
                <entry key="value" type="xstring" value="#404040"/>
            </config>
        </config>
        <config key="row_30">
            <entry key="rowKey" type="xstring" value="30"/>
            <config key="values">
                <entry key="array-size" type="xint" value="5"/>
                <entry key="0" type="xstring" value="30.0"/>
                <entry key="1" type="xstring" value="0.10461706048599027"/>
                <entry key="2" type="xstring" value="-0.10461706048599027"/>
                <entry key="3" type="xstring" value="-0.04139103875792908"/>
                <entry key="4" type="xstring" value="-0.06519361622151362"/>
            </config>
            <entry key="numProperties" type="xint" value="1"/>
            <config key="property_0">
                <entry key="key" type="xstring" value="color"/>
                <entry key="value" type="xstring" value="#404040"/>
            </config>
        </config>
        <config key="row_31">
            <entry key="rowKey" type="xstring" value="31"/>
            <config key="values">
                <entry key="array-size" type="xint" value="5"/>
                <entry key="0" type="xstring" value="31.0"/>
                <entry key="1" type="xstring" value="0.10476640682967035"/>
                <entry key="2" type="xstring" value="-0.10476640682967035"/>
                <entry key="3" type="xstring" value="-0.048516259439272895"/>
                <entry key="4" type="xstring" value="-0.04023895086714013"/>
            </config>
            <entry key="numProperties" type="xint" value="1"/>
            <config key="property_0">
                <entry key="key" type="xstring" value="color"/>
                <entry key="value" type="xstring" value="#404040"/>
            </config>
        </config>
        <config key="row_32">
            <entry key="rowKey" type="xstring" value="32"/>
            <config key="values">
                <entry key="array-size" type="xint" value="5"/>
                <entry key="0" type="xstring" value="32.0"/>
                <entry key="1" type="xstring" value="0.10491639460414909"/>
                <entry key="2" type="xstring" value="-0.10491639460414909"/>
                <entry key="3" type="xstring" value="-0.08304592236004564"/>
                <entry key="4" type="xstring" value="-0.08091603330709744"/>
            </config>
            <entry key="numProperties" type="xint" value="1"/>
            <config key="property_0">
                <entry key="key" type="xstring" value="color"/>
                <entry key="value" type="xstring" value="#404040"/>
            </config>
        </config>
        <config key="row_33">
            <entry key="rowKey" type="xstring" value="33"/>
            <config key="values">
                <entry key="array-size" type="xint" value="5"/>
                <entry key="0" type="xstring" value="33.0"/>
                <entry key="1" type="xstring" value="0.10506702841410388"/>
                <entry key="2" type="xstring" value="-0.10506702841410388"/>
                <entry key="3" type="xstring" value="-0.031491960312404595"/>
                <entry key="4" type="xstring" value="0.024621752781110777"/>
            </config>
            <entry key="numProperties" type="xint" value="1"/>
            <config key="property_0">
                <entry key="key" type="xstring" value="color"/>
                <entry key="value" type="xstring" value="#404040"/>
            </config>
        </config>
        <config key="row_34">
            <entry key="rowKey" type="xstring" value="34"/>
            <config key="values">
                <entry key="array-size" type="xint" value="5"/>
                <entry key="0" type="xstring" value="34.0"/>
                <entry key="1" type="xstring" value="0.10521831291062372"/>
                <entry key="2" type="xstring" value="-0.10521831291062372"/>
                <entry key="3" type="xstring" value="-0.06674556164081034"/>
                <entry key="4" type="xstring" value="-0.02326070158126697"/>
            </config>
            <entry key="numProperties" type="xint" value="1"/>
            <config key="property_0">
                <entry key="key" type="xstring" value="color"/>
                <entry key="value" type="xstring" value="#404040"/>
            </config>
        </config>
        <config key="row_35">
            <entry key="rowKey" type="xstring" value="35"/>
            <config key="values">
                <entry key="array-size" type="xint" value="5"/>
                <entry key="0" type="xstring" value="35.0"/>
                <entry key="1" type="xstring" value="0.10537025279181218"/>
                <entry key="2" type="xstring" value="-0.10537025279181218"/>
                <entry key="3" type="xstring" value="-0.022065020861386966"/>
                <entry key="4" type="xstring" value="0.014997944923469238"/>
            </config>
            <entry key="numProperties" type="xint" value="1"/>
            <config key="property_0">
                <entry key="key" type="xstring" value="color"/>
                <entry key="value" type="xstring" value="#404040"/>
            </config>
        </config>
        <config key="row_36">
            <entry key="rowKey" type="xstring" value="36"/>
            <config key="values">
                <entry key="array-size" type="xint" value="5"/>
                <entry key="0" type="xstring" value="36.0"/>
                <entry key="1" type="xstring" value="0.10552285280340044"/>
                <entry key="2" type="xstring" value="-0.10552285280340044"/>
                <entry key="3" type="xstring" value="-0.07103708728390637"/>
                <entry key="4" type="xstring" value="0.008226277820111766"/>
            </config>
            <entry key="numProperties" type="xint" value="1"/>
            <config key="property_0">
                <entry key="key" type="xstring" value="color"/>
                <entry key="value" type="xstring" value="#404040"/>
            </config>
        </config>
        <config key="row_37">
            <entry key="rowKey" type="xstring" value="37"/>
            <config key="values">
                <entry key="array-size" type="xint" value="5"/>
                <entry key="0" type="xstring" value="37.0"/>
                <entry key="1" type="xstring" value="0.10567611773936965"/>
                <entry key="2" type="xstring" value="-0.10567611773936965"/>
                <entry key="3" type="xstring" value="-0.001350130396361906"/>
                <entry key="4" type="xstring" value="0.11411046946111932"/>
            </config>
            <entry key="numProperties" type="xint" value="1"/>
            <config key="property_0">
                <entry key="key" type="xstring" value="color"/>
                <entry key="value" type="xstring" value="#404040"/>
            </config>
        </config>
        <config key="row_38">
            <entry key="rowKey" type="xstring" value="38"/>
            <config key="values">
                <entry key="array-size" type="xint" value="5"/>
                <entry key="0" type="xstring" value="38.0"/>
                <entry key="1" type="xstring" value="0.10583005244258362"/>
                <entry key="2" type="xstring" value="-0.10583005244258362"/>
                <entry key="3" type="xstring" value="-0.006608098820114753"/>
                <entry key="4" type="xstring" value="0.10541649752472414"/>
            </config>
            <entry key="numProperties" type="xint" value="1"/>
            <config key="property_0">
                <entry key="key" type="xstring" value="color"/>
                <entry key="value" type="xstring" value="#404040"/>
            </config>
        </config>
        <config key="row_39">
            <entry key="rowKey" type="xstring" value="39"/>
            <config key="values">
                <entry key="array-size" type="xint" value="5"/>
                <entry key="0" type="xstring" value="39.0"/>
                <entry key="1" type="xstring" value="0.10598466180543152"/>
                <entry key="2" type="xstring" value="-0.10598466180543152"/>
                <entry key="3" type="xstring" value="-0.021304099301812963"/>
                <entry key="4" type="xstring" value="0.02499709596182109"/>
            </config>
            <entry key="numProperties" type="xint" value="1"/>
            <config key="property_0">
                <entry key="key" type="xstring" value="color"/>
                <entry key="value" type="xstring" value="#404040"/>
            </config>
        </config>
        <config key="row_40">
            <entry key="rowKey" type="xstring" value="40"/>
            <config key="values">
                <entry key="array-size" type="xint" value="5"/>
                <entry key="0" type="xstring" value="40.0"/>
                <entry key="1" type="xstring" value="0.10613995077048094"/>
                <entry key="2" type="xstring" value="-0.10613995077048094"/>
                <entry key="3" type="xstring" value="-0.09067646265273685"/>
                <entry key="4" type="xstring" value="-0.10450741021423204"/>
            </config>
            <entry key="numProperties" type="xint" value="1"/>
            <config key="property_0">
                <entry key="key" type="xstring" value="color"/>
                <entry key="value" type="xstring" value="#404040"/>
            </config>
        </config>
        <config key="row_41">
            <entry key="rowKey" type="xstring" value="41"/>
            <config key="values">
                <entry key="array-size" type="xint" value="5"/>
                <entry key="0" type="xstring" value="41.0"/>
                <entry key="1" type="xstring" value="0.10629592433114153"/>
                <entry key="2" type="xstring" value="-0.10629592433114153"/>
                <entry key="3" type="xstring" value="-0.07256988579948545"/>
                <entry key="4" type="xstring" value="-0.006479531634014794"/>
            </config>
            <entry key="numProperties" type="xint" value="1"/>
            <config key="property_0">
                <entry key="key" type="xstring" value="color"/>
                <entry key="value" type="xstring" value="#404040"/>
            </config>
        </config>
        <config key="row_42">
            <entry key="rowKey" type="xstring" value="42"/>
            <config key="values">
                <entry key="array-size" type="xint" value="5"/>
                <entry key="0" type="xstring" value="42.0"/>
                <entry key="1" type="xstring" value="0.10645258753233941"/>
                <entry key="2" type="xstring" value="-0.10645258753233941"/>
                <entry key="3" type="xstring" value="-0.05115758287268283"/>
                <entry key="4" type="xstring" value="-0.019016431847644854"/>
            </config>
            <entry key="numProperties" type="xint" value="1"/>
            <config key="property_0">
                <entry key="key" type="xstring" value="color"/>
                <entry key="value" type="xstring" value="#404040"/>
            </config>
        </config>
        <config key="row_43">
            <entry key="rowKey" type="xstring" value="43"/>
            <config key="values">
                <entry key="array-size" type="xint" value="5"/>
                <entry key="0" type="xstring" value="43.0"/>
                <entry key="1" type="xstring" value="0.10660994547120255"/>
                <entry key="2" type="xstring" value="-0.10660994547120255"/>
                <entry key="3" type="xstring" value="-0.061253606894879346"/>
                <entry key="4" type="xstring" value="-0.0035283352363562085"/>
            </config>
            <entry key="numProperties" type="xint" value="1"/>
            <config key="property_0">
                <entry key="key" type="xstring" value="color"/>
                <entry key="value" type="xstring" value="#404040"/>
            </config>
        </config>
        <config key="row_44">
            <entry key="rowKey" type="xstring" value="44"/>
            <config key="values">
                <entry key="array-size" type="xint" value="5"/>
                <entry key="0" type="xstring" value="44.0"/>
                <entry key="1" type="xstring" value="0.10676800329775729"/>
                <entry key="2" type="xstring" value="-0.10676800329775729"/>
                <entry key="3" type="xstring" value="-0.06149761991883957"/>
                <entry key="4" type="xstring" value="-0.00728114229921338"/>
            </config>
            <entry key="numProperties" type="xint" value="1"/>
            <config key="property_0">
                <entry key="key" type="xstring" value="color"/>
                <entry key="value" type="xstring" value="#404040"/>
            </config>
        </config>
        <config key="row_45">
            <entry key="rowKey" type="xstring" value="45"/>
            <config key="values">
                <entry key="array-size" type="xint" value="5"/>
                <entry key="0" type="xstring" value="45.0"/>
                <entry key="1" type="xstring" value="0.10692676621563627"/>
                <entry key="2" type="xstring" value="-0.10692676621563627"/>
                <entry key="3" type="xstring" value="-0.07719956721170154"/>
                <entry key="4" type="xstring" value="-0.02125468964977666"/>
            </config>
            <entry key="numProperties" type="xint" value="1"/>
            <config key="property_0">
                <entry key="key" type="xstring" value="color"/>
                <entry key="value" type="xstring" value="#404040"/>
            </config>
        </config>
        <config key="row_46">
            <entry key="rowKey" type="xstring" value="46"/>
            <config key="values">
                <entry key="array-size" type="xint" value="5"/>
                <entry key="0" type="xstring" value="46.0"/>
                <entry key="1" type="xstring" value="0.107086239482798"/>
                <entry key="2" type="xstring" value="-0.107086239482798"/>
                <entry key="3" type="xstring" value="-0.09944866275818398"/>
                <entry key="4" type="xstring" value="-0.024814434069867303"/>
            </config>
            <entry key="numProperties" type="xint" value="1"/>
            <config key="property_0">
                <entry key="key" type="xstring" value="color"/>
                <entry key="value" type="xstring" value="#404040"/>
            </config>
        </config>
        <config key="row_47">
            <entry key="rowKey" type="xstring" value="47"/>
            <config key="values">
                <entry key="array-size" type="xint" value="5"/>
                <entry key="0" type="xstring" value="47.0"/>
                <entry key="1" type="xstring" value="0.10724642841225822"/>
                <entry key="2" type="xstring" value="-0.10724642841225822"/>
                <entry key="3" type="xstring" value="-0.12393729105286781"/>
                <entry key="4" type="xstring" value="-0.05323416425079031"/>
            </config>
            <entry key="numProperties" type="xint" value="1"/>
            <config key="property_0">
                <entry key="key" type="xstring" value="color"/>
                <entry key="value" type="xstring" value="#404040"/>
            </config>
        </config>
        <config key="row_48">
            <entry key="rowKey" type="xstring" value="48"/>
            <config key="values">
                <entry key="array-size" type="xint" value="5"/>
                <entry key="0" type="xstring" value="48.0"/>
                <entry key="1" type="xstring" value="0.10740733837283342"/>
                <entry key="2" type="xstring" value="-0.10740733837283342"/>
                <entry key="3" type="xstring" value="-0.0775895869073104"/>
                <entry key="4" type="xstring" value="0.013766588922200219"/>
            </config>
            <entry key="numProperties" type="xint" value="1"/>
            <config key="property_0">
                <entry key="key" type="xstring" value="color"/>
                <entry key="value" type="xstring" value="#404040"/>
            </config>
        </config>
        <config key="row_49">
            <entry key="rowKey" type="xstring" value="49"/>
            <config key="values">
                <entry key="array-size" type="xint" value="5"/>
                <entry key="0" type="xstring" value="49.0"/>
                <entry key="1" type="xstring" value="0.10756897478989653"/>
                <entry key="2" type="xstring" value="-0.10756897478989653"/>
                <entry key="3" type="xstring" value="-0.1127099574317319"/>
                <entry key="4" type="xstring" value="-0.07458669528726657"/>
            </config>
            <entry key="numProperties" type="xint" value="1"/>
            <config key="property_0">
                <entry key="key" type="xstring" value="color"/>
                <entry key="value" type="xstring" value="#404040"/>
            </config>
        </config>
        <config key="row_50">
            <entry key="rowKey" type="xstring" value="50"/>
            <config key="values">
                <entry key="array-size" type="xint" value="5"/>
                <entry key="0" type="xstring" value="50.0"/>
                <entry key="1" type="xstring" value="0.10773134314614528"/>
                <entry key="2" type="xstring" value="-0.10773134314614528"/>
                <entry key="3" type="xstring" value="-0.2064591347631422"/>
                <entry key="4" type="xstring" value="-0.20782067358334816"/>
            </config>
            <entry key="numProperties" type="xint" value="1"/>
            <config key="property_0">
                <entry key="key" type="xstring" value="color"/>
                <entry key="value" type="xstring" value="#404040"/>
            </config>
        </config>
        <config key="row_51">
            <entry key="rowKey" type="xstring" value="51"/>
            <config key="values">
                <entry key="array-size" type="xint" value="5"/>
                <entry key="0" type="xstring" value="51.0"/>
                <entry key="1" type="xstring" value="0.10789444898238335"/>
                <entry key="2" type="xstring" value="-0.10789444898238335"/>
                <entry key="3" type="xstring" value="-0.15578846046822284"/>
                <entry key="4" type="xstring" value="-0.06918856770682937"/>
            </config>
            <entry key="numProperties" type="xint" value="1"/>
            <config key="property_0">
                <entry key="key" type="xstring" value="color"/>
                <entry key="value" type="xstring" value="#404040"/>
            </config>
        </config>
        <config key="row_52">
            <entry key="rowKey" type="xstring" value="52"/>
            <config key="values">
                <entry key="array-size" type="xint" value="5"/>
                <entry key="0" type="xstring" value="52.0"/>
                <entry key="1" type="xstring" value="0.10805829789831436"/>
                <entry key="2" type="xstring" value="-0.10805829789831436"/>
                <entry key="3" type="xstring" value="-0.17366988354224688"/>
                <entry key="4" type="xstring" value="-0.09080475364315159"/>
            </config>
            <entry key="numProperties" type="xint" value="1"/>
            <config key="property_0">
                <entry key="key" type="xstring" value="color"/>
                <entry key="value" type="xstring" value="#404040"/>
            </config>
        </config>
        <config key="row_53">
            <entry key="rowKey" type="xstring" value="53"/>
            <config key="values">
                <entry key="array-size" type="xint" value="5"/>
                <entry key="0" type="xstring" value="53.0"/>
                <entry key="1" type="xstring" value="0.1082228955533496"/>
                <entry key="2" type="xstring" value="-0.1082228955533496"/>
                <entry key="3" type="xstring" value="-0.1111687310037263"/>
                <entry key="4" type="xstring" value="0.03505738332600136"/>
            </config>
            <entry key="numProperties" type="xint" value="1"/>
            <config key="property_0">
                <entry key="key" type="xstring" value="color"/>
                <entry key="value" type="xstring" value="#404040"/>
            </config>
        </config>
        <config key="row_54">
            <entry key="rowKey" type="xstring" value="54"/>
            <config key="values">
                <entry key="array-size" type="xint" value="5"/>
                <entry key="0" type="xstring" value="54.0"/>
                <entry key="1" type="xstring" value="0.10838824766742888"/>
                <entry key="2" type="xstring" value="-0.10838824766742888"/>
                <entry key="3" type="xstring" value="-0.1646011311808213"/>
                <entry key="4" type="xstring" value="0.0036857248565447466"/>
            </config>
            <entry key="numProperties" type="xint" value="1"/>
            <config key="property_0">
                <entry key="key" type="xstring" value="color"/>
                <entry key="value" type="xstring" value="#404040"/>
            </config>
        </config>
        <config key="row_55">
            <entry key="rowKey" type="xstring" value="55"/>
            <config key="values">
                <entry key="array-size" type="xint" value="5"/>
                <entry key="0" type="xstring" value="55.0"/>
                <entry key="1" type="xstring" value="0.10855436002185541"/>
                <entry key="2" type="xstring" value="-0.10855436002185541"/>
                <entry key="3" type="xstring" value="-0.08589214129535366"/>
                <entry key="4" type="xstring" value="0.10900680909992655"/>
            </config>
            <entry key="numProperties" type="xint" value="1"/>
            <config key="property_0">
                <entry key="key" type="xstring" value="color"/>
                <entry key="value" type="xstring" value="#404040"/>
            </config>
        </config>
        <config key="row_56">
            <entry key="rowKey" type="xstring" value="56"/>
            <config key="values">
                <entry key="array-size" type="xint" value="5"/>
                <entry key="0" type="xstring" value="56.0"/>
                <entry key="1" type="xstring" value="0.1087212384601449"/>
                <entry key="2" type="xstring" value="-0.1087212384601449"/>
                <entry key="3" type="xstring" value="-0.14404179338460305"/>
                <entry key="4" type="xstring" value="-0.033007528810945104"/>
            </config>
            <entry key="numProperties" type="xint" value="1"/>
            <config key="property_0">
                <entry key="key" type="xstring" value="color"/>
                <entry key="value" type="xstring" value="#404040"/>
            </config>
        </config>
        <config key="row_57">
            <entry key="rowKey" type="xstring" value="57"/>
            <config key="values">
                <entry key="array-size" type="xint" value="5"/>
                <entry key="0" type="xstring" value="57.0"/>
                <entry key="1" type="xstring" value="0.10888888888888888"/>
                <entry key="2" type="xstring" value="-0.10888888888888888"/>
                <entry key="3" type="xstring" value="-0.13242690221121778"/>
                <entry key="4" type="xstring" value="-0.0053579620648955195"/>
            </config>
            <entry key="numProperties" type="xint" value="1"/>
            <config key="property_0">
                <entry key="key" type="xstring" value="color"/>
                <entry key="value" type="xstring" value="#404040"/>
            </config>
        </config>
        <config key="row_58">
            <entry key="rowKey" type="xstring" value="58"/>
            <config key="values">
                <entry key="array-size" type="xint" value="5"/>
                <entry key="0" type="xstring" value="58.0"/>
                <entry key="1" type="xstring" value="0.10905731727863281"/>
                <entry key="2" type="xstring" value="-0.10905731727863281"/>
                <entry key="3" type="xstring" value="-0.13862074027771637"/>
                <entry key="4" type="xstring" value="-0.05513456546407613"/>
            </config>
            <entry key="numProperties" type="xint" value="1"/>
            <config key="property_0">
                <entry key="key" type="xstring" value="color"/>
                <entry key="value" type="xstring" value="#404040"/>
            </config>
        </config>
        <config key="row_59">
            <entry key="rowKey" type="xstring" value="59"/>
            <config key="values">
                <entry key="array-size" type="xint" value="5"/>
                <entry key="0" type="xstring" value="59.0"/>
                <entry key="1" type="xstring" value="0.10922652966476915"/>
                <entry key="2" type="xstring" value="-0.10922652966476915"/>
                <entry key="3" type="xstring" value="-0.10621367154682766"/>
                <entry key="4" type="xstring" value="0.03845808709003616"/>
            </config>
            <entry key="numProperties" type="xint" value="1"/>
            <config key="property_0">
                <entry key="key" type="xstring" value="color"/>
                <entry key="value" type="xstring" value="#404040"/>
            </config>
        </config>
        <config key="row_60">
            <entry key="rowKey" type="xstring" value="60"/>
            <config key="values">
                <entry key="array-size" type="xint" value="5"/>
                <entry key="0" type="xstring" value="60.0"/>
                <entry key="1" type="xstring" value="0.10939653214844572"/>
                <entry key="2" type="xstring" value="-0.10939653214844572"/>
                <entry key="3" type="xstring" value="-0.09565958003502821"/>
                <entry key="4" type="xstring" value="0.019746070354930447"/>
            </config>
            <entry key="numProperties" type="xint" value="1"/>
            <config key="property_0">
                <entry key="key" type="xstring" value="color"/>
                <entry key="value" type="xstring" value="#404040"/>
            </config>
        </config>
        <entry key="numColorModels" type="xint" value="0"/>
        <config key="missingValueColumns">
            <entry key="array-size" type="xint" value="0"/>
        </config>
    </config>
    <entry key="displayFullscreenButton" type="xboolean" value="true"/>
    <entry key="missingValueMethod" type="xstring" value="noGap"/>
    <entry key="showWarningInView" type="xboolean" value="true"/>
    <entry key="hasWarnings" type="xboolean" value="false"/>
    <entry key="reportOnMissingValues" type="xboolean" value="true"/>
    <config key="dateTimeFormats">
        <entry key="globalDateTimeLocale" type="xstring" value="en"/>
        <entry key="globalDateFormat" type="xstring" value="YYYY-MM-DD"/>
        <entry key="globalLocalDateFormat" type="xstring" value="YYYY-MM-DD"/>
        <entry key="globalLocalDateTimeFormat" type="xstring" value="YYYY-MM-DD"/>
        <entry key="globalLocalTimeFormat" type="xstring" value="HH:mm:ss"/>
        <entry key="globalZonedDateTimeFormat" type="xstring" value="YYYY-MM-DD z"/>
        <entry key="timezone" type="xstring" value="Europe/Berlin"/>
    </config>
    <entry key="enforceOrigin" type="xboolean" value="false"/>
    <entry key="enableLineSizeChange" type="xboolean" value="false"/>
</config>
